myypy/__init__.py
myypy-0.1.0.dist-info/METADATA
myypy-0.1.0.dist-info/WHEEL
myypy-0.1.0.dist-info/licenses/LICENSE
myypy-0.1.0.dist-info/RECORD
