Metadata-Version: 2.1
Name: myypy
Version: 0.1.0
Summary: Python bindings for Yrs
Project-URL: Homepage, https://github.com/davidbrochart/myypy
Author-email: David Brochart <david.brochart@gmail.com>
License: The MIT License (MIT)
License-File: LICENSE
Keywords: crdt
Classifier: Development Status :: 4 - Beta
Classifier: Intended Audience :: Developers
Classifier: License :: OSI Approved :: MIT License
Classifier: Programming Language :: Python
Classifier: Programming Language :: Python :: 3.7
Classifier: Programming Language :: Python :: 3.8
Classifier: Programming Language :: Python :: 3.9
Classifier: Programming Language :: Python :: 3.10
Classifier: Programming Language :: Python :: 3.11
Classifier: Programming Language :: Rust
